tcool_pylib/__init__.py
tcool_pylib/hello.py
tcool_pylib-1.0.0.dist-info/METADATA
tcool_pylib-1.0.0.dist-info/WHEEL
tcool_pylib-1.0.0.dist-info/entry_points.txt
tcool_pylib-1.0.0.dist-info/top_level.txt
tcool_pylib-1.0.0.dist-info/RECORD
