Metadata-Version: 2.1
Name: tcool-pylib
Version: 1.0.0
Summary: A template to generate Python library
Home-page: https://github.com/t-cool/pylib
Author: t-cool
Author-email: UNKNOWN
License: UNKNOWN
Platform: UNKNOWN
Requires-Dist: requests
